idiot/api.py
idiot/resources.py
idiot/__init__.py
idiot-0.1.0.dist-info/DESCRIPTION.rst
idiot-0.1.0.dist-info/METADATA
idiot-0.1.0.dist-info/metadata.json
idiot-0.1.0.dist-info/RECORD
idiot-0.1.0.dist-info/top_level.txt
idiot-0.1.0.dist-info/WHEEL
